chameleon_flask/__init__.py
chameleon_flask/engine.py
chameleon_flask/exceptions.py
chameleon_flask-0.5.1.dist-info/METADATA
chameleon_flask-0.5.1.dist-info/WHEEL
chameleon_flask-0.5.1.dist-info/licenses/LICENSE
chameleon_flask-0.5.1.dist-info/RECORD
