Metadata-Version: 2.4
Name: chameleon_flask
Version: 0.5.1
Summary: Adds integration of the Chameleon template language to Flask and Quart.
Project-URL: Homepage, https://github.com/mikeckennedy/chameleon-flask
Author-email: Michael Kennedy <michael@talkpython.fm>
License: MIT
License-File: LICENSE
Keywords: Chameleon,Flask,integration,template
Classifier: Development Status :: 4 - Beta
Classifier: License :: OSI Approved :: MIT License
Classifier: Programming Language :: Python
Classifier: Programming Language :: Python :: 3.10
Classifier: Programming Language :: Python :: 3.11
Classifier: Programming Language :: Python :: 3.12
Classifier: Programming Language :: Python :: 3.13
Requires-Python: >=3.10
Requires-Dist: chameleon
Requires-Dist: flask[async]
